CHANGES.txt
README.rst
setup.cfg
setup.py
deform_widget_jquery_option_tree/__init__.py
deform_widget_jquery_option_tree/tests.py
deform_widget_jquery_option_tree.egg-info/PKG-INFO
deform_widget_jquery_option_tree.egg-info/SOURCES.txt
deform_widget_jquery_option_tree.egg-info/dependency_links.txt
deform_widget_jquery_option_tree.egg-info/not-zip-safe
deform_widget_jquery_option_tree.egg-info/requires.txt
deform_widget_jquery_option_tree.egg-info/top_level.txt
deform_widget_jquery_option_tree/static/jquery.js
deform_widget_jquery_option_tree/static/jquery.optionTree.js
deform_widget_jquery_option_tree/templates/jquery_option_tree.pt
deform_widget_jquery_option_tree/templates/readonly/jquery_option_tree.pt
demo/app.py
demo/index.pt