Metadata-Version: 1.0
Name: deform-widget-jquery-option-tree
Version: 0.2.1
Summary: jQuery Option Tree widget for deform
Home-page: https://github.com/disko/deform_widget_jquery_option_tree
Author: Andreas Kaiser
Author-email: disko@binary-punks.com
License: MIT
Keywords: deform widget
Platform: UNKNOWN
Classifier: Environment :: Plugins
Classifier: Environment :: Web Environment
Classifier: Intended Audience :: Developers
Classifier: License :: OSI Approved :: MIT License
Classifier: Programming Language :: Python
